setup.py
scripts/xenrt
scripts/xenrtnew
xenrtapi/__init__.py
xenrtapi.egg-info/PKG-INFO
xenrtapi.egg-info/SOURCES.txt
xenrtapi.egg-info/dependency_links.txt
xenrtapi.egg-info/requires.txt
xenrtapi.egg-info/top_level.txt
xenrtapi.egg-info/zip-safe