Metadata-Version: 1.0
Name: xenrtapi
Version: 0.15
Summary: API for XenRT
Home-page: https://xenrt.citrite.net
Author: Citrix
Author-email: svcacct_xs_xenrt@citrix.com
License: Apache
Platform: UNKNOWN
